__init__.py
my_logger.py
onlinetorch_my_logger-0.2.2.dist-info/DESCRIPTION.rst
onlinetorch_my_logger-0.2.2.dist-info/METADATA
onlinetorch_my_logger-0.2.2.dist-info/RECORD
onlinetorch_my_logger-0.2.2.dist-info/WHEEL
onlinetorch_my_logger-0.2.2.dist-info/metadata.json
onlinetorch_my_logger-0.2.2.dist-info/top_level.txt
