Metadata-Version: 2.0
Name: onlinetorch-my-logger
Version: 0.2.2
Summary: Python Onlinetorch Project MyLogger
Home-page: UNKNOWN
Author: Benedikt Schmeitz
Author-email: UNKNOWN
License: UNKNOWN
Platform: UNKNOWN
